pyreunion-0.1.3.dist-info/METADATA
pyreunion-0.1.3.dist-info/WHEEL
pyreunion/__init__.py
pyreunion/pyreunion.cpython-39-x86_64-linux-gnu.so
pyreunion-0.1.3.dist-info/RECORD
