Metadata-Version: 2.1
Name: pyreunion
Version: 0.1.3
Classifier: Programming Language :: Python
Summary: A Python API for the Rust backend of `reunion`, i.e. a Union-Find w/ Rank data
Keywords: Union Find,Algorithms,Data Structures,Disjoint Set
Author: Aalekh Patel <aalekh.gwpeck.7998@icloud.com>
Author-email: Aalekh Patel <aalekh.gwpeck.7998@icloud.com>
Maintainer-email: Aalekh Patel <aalekh.gwpeck.7998@icloud.com>
License: Copyright 2021 Aalekh Patel <aalekh.gwpeck.7998@icloud.com>
Requires-Python: >=3.8
Project-URL: Source Code, https://www.github.com/aalekhpatel07/reunion-api
